biosignal_device_interface/__init__.py
biosignal_device_interface/constants/__init__.py
biosignal_device_interface/constants/devices/__init__.py
biosignal_device_interface/constants/devices/core/base_device_constants.py
biosignal_device_interface/constants/devices/otb/otb_constants.py
biosignal_device_interface/constants/devices/otb/otb_muovi_constants.py
biosignal_device_interface/constants/devices/otb/otb_quattrocento_constants.py
biosignal_device_interface/constants/devices/otb/otb_quattrocento_light_constants.py
biosignal_device_interface/constants/devices/otb/otb_syncstation_constants.py
biosignal_device_interface/constants/plots/color_palette.py
biosignal_device_interface/devices/__init__.py
biosignal_device_interface/devices/core/__init__.py
biosignal_device_interface/devices/core/base_device.py
biosignal_device_interface/devices/otb/__init__.py
biosignal_device_interface/devices/otb/otb_muovi.py
biosignal_device_interface/devices/otb/otb_quattrocento.py
biosignal_device_interface/devices/otb/otb_quattrocento_light.py
biosignal_device_interface/devices/otb/otb_syncstation.py
biosignal_device_interface/gui/device_template_widgets/__init__.py
biosignal_device_interface/gui/device_template_widgets/all_devices_widget.py
biosignal_device_interface/gui/device_template_widgets/core/base_device_widget.py
biosignal_device_interface/gui/device_template_widgets/core/base_multiple_devices_widget.py
biosignal_device_interface/gui/device_template_widgets/otb/__init__.py
biosignal_device_interface/gui/device_template_widgets/otb/otb_devices_widget.py
biosignal_device_interface/gui/device_template_widgets/otb/otb_muovi_plus_widget.py
biosignal_device_interface/gui/device_template_widgets/otb/otb_muovi_widget.py
biosignal_device_interface/gui/device_template_widgets/otb/otb_quattrocento_light_widget.py
biosignal_device_interface/gui/device_template_widgets/otb/otb_quattrocento_widget.py
biosignal_device_interface/gui/device_template_widgets/otb/otb_syncstation_widget.py
biosignal_device_interface-0.2.2.dist-info/METADATA
biosignal_device_interface-0.2.2.dist-info/WHEEL
biosignal_device_interface-0.2.2.dist-info/licenses/LICENSE
biosignal_device_interface-0.2.2.dist-info/RECORD
