Metadata-Version: 2.4
Name: biosignal-device-interface
Version: 0.2.2
Summary: Python communication interface to many biosignal devices manufactured by several companies to easy integration in custom PySide6 applications.
License: CC BY-SA 4.0
License-File: LICENSE
Author: Dominik I. Braun
Author-email: dome.braun@fau.de
Requires-Python: >=3.10,<3.13
Classifier: License :: Other/Proprietary License
Classifier: Programming Language :: Python :: 3
Classifier: Programming Language :: Python :: 3.10
Classifier: Programming Language :: Python :: 3.11
Classifier: Programming Language :: Python :: 3.12
Requires-Dist: aenum (>=3.1.15,<4.0.0)
Requires-Dist: matplotlib (>=3.9.0,<4.0.0)
Requires-Dist: numpy (>=1.26.4,<2.0.0)
Requires-Dist: psutil (>=5.9.8,<6.0.0)
Requires-Dist: pyside6 (>=6.7.0,<7.0.0)
Requires-Dist: scipy (>=1.14.0,<2.0.0)
Requires-Dist: tornado (>=6.4.2,<7.0.0)
Requires-Dist: vispy (>=0.14.3,<0.15.0)
